pysect/__init__.py
pysect/main.py
pysect/config/__init__.py
pysect/config/config.py
pysect/filament/__init__.py
pysect/filament/filament.py
pysect/primitives/__init__.py
pysect/primitives/coord.py
pysect/printer/__init__.py
pysect/printer/printer.py
pysect/sect/__init__.py
pysect/sect/config.py
pysect/sect/sect.py
pysect/sect/slice.py
pysect/sect/primitives/__init__.py
pysect/sect/primitives/mesh.py
pysect/sect/primitives/stl.py
pysect/sect/serial/__init__.py
pysect/sect/serial/stl.py
pysect/slice/__init__.py
pysect/slice/slice.py
pysect-0.0.3.dist-info/LICENSE
pysect-0.0.3.dist-info/METADATA
pysect-0.0.3.dist-info/WHEEL
pysect-0.0.3.dist-info/top_level.txt
pysect-0.0.3.dist-info/RECORD
